ipromise/__init__.py
ipromise/annotations.py
ipromise/augments.py
ipromise/implements.py
ipromise/ipromise.py
ipromise/overrides.py
ipromise/py.typed
ipromise/test/__init__.py
ipromise/test/common.py
ipromise/test/test_abc.py
ipromise/test/test_augments.py
ipromise/test/test_implements.py
ipromise/test/test_overrides.py
ipromise-1.9.dist-info/LICENSE
ipromise-1.9.dist-info/WHEEL
ipromise-1.9.dist-info/METADATA
ipromise-1.9.dist-info/RECORD
