Metadata-Version: 2.1
Name: ipromise
Version: 1.9
Summary: A Python base class that provides various decorators for specifying promises relating to inheritance.
Home-page: https://github.com/NeilGirdhar/ipromise
License: MIT
Author: Neil Girdhar
Author-email: mistersheik@gmail.com
Requires-Python: >=3.6,<4.0
Classifier: Development Status :: 5 - Production/Stable
Classifier: Intended Audience :: Developers
Classifier: License :: OSI Approved :: MIT License
Classifier: Operating System :: OS Independent
Classifier: Programming Language :: Python
Classifier: Programming Language :: Python :: 3
Classifier: Programming Language :: Python :: 3.6
Classifier: Programming Language :: Python :: 3.7
Classifier: Programming Language :: Python :: 3.8
Classifier: Topic :: Software Development :: Libraries :: Python Modules
Project-URL: Repository, https://github.com/NeilGirdhar/ipromise
